table2xsv/__init__.py
table2xsv/bin/__init__.py
table2xsv/bin/main.py
table2xsv/core/__init__.py
table2xsv/core/base.py
table2xsv/core/exceptions.py
table2xsv/core/formatter.py
table2xsv/core/helpers.py
table2xsv/core/parser.py
table2xsv/core/utility.py
table2xsv/core/wrapper.py
table2xsv/management/__init__.py
table2xsv/management/base.py
table2xsv/management/commands/__init__.py
table2xsv/management/commands/csv.py
table2xsv/management/commands/excel.py
table2xsv/management/commands/mysql.py
table2xsv/management/commands/neo4j.py
table2xsv/management/commands/sqlite.py
table2xsv/utils/__init__.py
table2xsv/utils/getter.py
Table2XSV-2.0.1.dist-info/LICENSE
Table2XSV-2.0.1.dist-info/METADATA
Table2XSV-2.0.1.dist-info/WHEEL
Table2XSV-2.0.1.dist-info/entry_points.txt
Table2XSV-2.0.1.dist-info/top_level.txt
Table2XSV-2.0.1.dist-info/RECORD
