Metadata-Version: 2.1
Name: Table2XSV
Version: 2.0.1
Summary: Convert Tabular Data to XSV
Home-page: https://github.com/amoghmadan/Table2XSV
Author: Amogh Madan
Author-email: amoghmadaan@gmail.com
License: MIT
Project-URL: Documentation, https://github.com/amoghmadan/Table2XSV
Platform: any
Classifier: Development Status :: 5 - Production/Stable
Classifier: Environment :: Console
Classifier: Intended Audience :: Developers
Classifier: Intended Audience :: System Administrators
Classifier: License :: OSI Approved :: MIT License
Classifier: Natural Language :: English
Classifier: Operating System :: OS Independent
Classifier: Programming Language :: Python
Classifier: Programming Language :: Python :: 3
Classifier: Programming Language :: Python :: 3 :: Only
Classifier: Programming Language :: Python :: 3.7
Classifier: Programming Language :: Python :: 3.8
Classifier: Programming Language :: Python :: 3.9
Classifier: Programming Language :: Python :: 3.10
Classifier: Topic :: Utilities
Requires-Python: <3.11,>=3.7
License-File: LICENSE
Requires-Dist: numpy (==1.21.4)
Requires-Dist: pandas (==1.3.4)
Requires-Dist: python-dateutil (==2.8.2)
Requires-Dist: pytz (==2021.3)
Requires-Dist: six (==1.16.0)
Provides-Extra: all
Requires-Dist: defusedxml (==0.7.1) ; extra == 'all'
Requires-Dist: et-xmlfile (==1.1.0) ; extra == 'all'
Requires-Dist: odfpy (==1.4.1) ; extra == 'all'
Requires-Dist: openpyxl (==3.0.9) ; extra == 'all'
Requires-Dist: pyxlsb (==1.0.9) ; extra == 'all'
Requires-Dist: xlrd (==2.0.1) ; extra == 'all'
Requires-Dist: mysqlclient (==2.1.0) ; extra == 'all'
Requires-Dist: pytz (==2021.3) ; extra == 'all'
Requires-Dist: neo4j (==4.4.0) ; extra == 'all'
Provides-Extra: excel
Requires-Dist: defusedxml (==0.7.1) ; extra == 'excel'
Requires-Dist: et-xmlfile (==1.1.0) ; extra == 'excel'
Requires-Dist: odfpy (==1.4.1) ; extra == 'excel'
Requires-Dist: openpyxl (==3.0.9) ; extra == 'excel'
Requires-Dist: pyxlsb (==1.0.9) ; extra == 'excel'
Requires-Dist: xlrd (==2.0.1) ; extra == 'excel'
Provides-Extra: mysql
Requires-Dist: mysqlclient (==2.1.0) ; extra == 'mysql'
Provides-Extra: neo4j
Requires-Dist: pytz (==2021.3) ; extra == 'neo4j'
Requires-Dist: neo4j (==4.4.0) ; extra == 'neo4j'
